slurm_time/__init__.py
slurm_time/_version.py
slurm_time/handlers.py
slurm_time/labextension/build_log.json
slurm_time/labextension/package.json
slurm_time/labextension/static/lib_index_js.0094cf24b9661ccb4290.js
slurm_time/labextension/static/lib_index_js.0094cf24b9661ccb4290.js.map
slurm_time/labextension/static/lib_index_js.688642114905690a5b9d.js
slurm_time/labextension/static/lib_index_js.688642114905690a5b9d.js.map
slurm_time/labextension/static/remoteEntry.53e8c1212778fdb14e68.js
slurm_time/labextension/static/remoteEntry.53e8c1212778fdb14e68.js.map
slurm_time/labextension/static/remoteEntry.81490697c58dedf0669b.js.map
slurm_time/labextension/static/style.js
slurm_time/labextension/static/style_index_js.77c13fc03a474f08deb6.js
slurm_time/labextension/static/style_index_js.77c13fc03a474f08deb6.js.map
slurm_time/labextension/static/vendors-node_modules_css-loader_dist_runtime_api_js-node_modules_css-loader_dist_runtime_cssW-72eba1.7a9cbb5ac647b68e3d10.js
slurm_time/labextension/static/vendors-node_modules_css-loader_dist_runtime_api_js-node_modules_css-loader_dist_runtime_cssW-72eba1.7a9cbb5ac647b68e3d10.js.map
slurm_time/tests/__init__.py
slurm_time/tests/test_handlers.py
slurm_time-0.1.0.data/data/etc/jupyter/jupyter_notebook_config.d/slurm_time.json
slurm_time-0.1.0.data/data/etc/jupyter/jupyter_server_config.d/slurm_time.json
slurm_time-0.1.0.data/data/share/jupyter/labextensions/slurm-time/build_log.json
slurm_time-0.1.0.data/data/share/jupyter/labextensions/slurm-time/install.json
slurm_time-0.1.0.data/data/share/jupyter/labextensions/slurm-time/package.json
slurm_time-0.1.0.data/data/share/jupyter/labextensions/slurm-time/static/lib_index_js.0094cf24b9661ccb4290.js
slurm_time-0.1.0.data/data/share/jupyter/labextensions/slurm-time/static/lib_index_js.0094cf24b9661ccb4290.js.map
slurm_time-0.1.0.data/data/share/jupyter/labextensions/slurm-time/static/lib_index_js.688642114905690a5b9d.js
slurm_time-0.1.0.dist-info/LICENSE
slurm_time-0.1.0.dist-info/METADATA
slurm_time-0.1.0.dist-info/WHEEL
slurm_time-0.1.0.dist-info/top_level.txt
slurm_time-0.1.0.dist-info/RECORD
